{"nm":"boton1","ddd":1,"h":100,"w":100,"meta":{"g":"@lottiefiles/toolkit-js 0.33.2"},"layers":[{"ty":0,"nm":"play","sr":1,"st":0,"op":192.4,"ip":0,"hd":false,"ddd":1,"bm":0,"hasMask":false,"ao":0,"ks":{"a":{"a":0,"k":[359,305,0],"ix":1},"s":{"a":0,"k":[11,11,11],"ix":6},"sk":{"a":0,"k":0},"p":{"a":0,"k":[-546.333,-151.917,0],"ix":2},"sa":{"a":0,"k":0},"o":{"a":0,"k":100,"ix":11},"rx":{"a":0,"k":0,"ix":8},"ry":{"a":0,"k":0,"ix":9},"rz":{"a":0,"k":0,"ix":10},"or":{"a":0,"k":[330,0,0],"ix":7}},"ef":[],"w":718,"h":610,"refId":"comp_0","ind":1,"parent":2},{"ty":4,"nm":"botonarriba","sr":1,"st":0,"op":99,"ip":0,"hd":false,"ddd":0,"bm":0,"hasMask":false,"ao":0,"ks":{"a":{"a":0,"k":[-547.664,-150.675,0],"ix":1},"s":{"a":0,"k":[25.97,27.62,100],"ix":6},"sk":{"a":0,"k":0},"p":{"a":1,"k":[{"o":{"x":0.333,"y":0},"i":{"x":0.667,"y":1},"s":[49.91,43.37,0],"t":28},{"o":{"x":0.333,"y":0},"i":{"x":0.667,"y":1},"s":[49.91,45.3,0],"t":33},{"s":[49.91,43.37,0],"t":38}],"ix":2},"r":{"a":0,"k":0,"ix":10},"sa":{"a":0,"k":0},"o":{"a":0,"k":100,"ix":11}},"ef":[],"shapes":[{"ty":"gr","bm":0,"hd":false,"mn":"ADBE Vector Group","nm":"Elipse 1","ix":1,"cix":2,"np":3,"it":[{"ty":"el","bm":0,"hd":false,"mn":"ADBE Vector Shape - Ellipse","nm":"Trazado elíptico 1","d":1,"p":{"a":0,"k":[0,0],"ix":3},"s":{"a":0,"k":[236.46,160.849],"ix":2}},{"ty":"st","bm":0,"hd":false,"mn":"ADBE Vector Graphic - Stroke","nm":"Trazo 1","lc":1,"lj":1,"ml":4,"o":{"a":0,"k":100,"ix":4},"w":{"a":0,"k":4,"ix":5},"c":{"a":0,"k":[0.2078,0.2039,0.2039],"ix":3}},{"ty":"fl","bm":0,"hd":false,"mn":"ADBE Vector Graphic - Fill","nm":"Relleno 1","c":{"a":1,"k":[{"o":{"x":0.333,"y":0},"i":{"x":0.667,"y":1},"s":[0.9451,0.2706,0.4275],"t":28},{"o":{"x":0.167,"y":0},"i":{"x":0.667,"y":1},"s":[0.2471,0.8353,0.349],"t":33},{"s":[0.2471,0.8353,0.349],"t":46}],"ix":4},"r":1,"o":{"a":0,"k":100,"ix":5}},{"ty":"tr","a":{"a":0,"k":[0,0],"ix":1},"s":{"a":0,"k":[57.884,57.884],"ix":3},"sk":{"a":0,"k":0,"ix":4},"p":{"a":0,"k":[-547.664,-150.675],"ix":2},"r":{"a":0,"k":0,"ix":6},"sa":{"a":0,"k":0,"ix":5},"o":{"a":0,"k":100,"ix":7}}]}],"ind":2},{"ty":4,"nm":"Boton1","sr":1,"st":0,"op":99,"ip":0,"hd":false,"ddd":0,"bm":0,"hasMask":false,"ao":0,"ks":{"a":{"a":0,"k":[-551.445,-111.847,0],"ix":1},"s":{"a":0,"k":[15.06,16.02,100],"ix":6},"sk":{"a":0,"k":0},"p":{"a":0,"k":[49.67,49.92,0],"ix":2},"r":{"a":0,"k":0,"ix":10},"sa":{"a":0,"k":0},"o":{"a":0,"k":100,"ix":11}},"ef":[],"shapes":[{"ty":"gr","bm":0,"hd":false,"mn":"ADBE Vector Group","nm":"abajo","ix":2,"cix":2,"np":3,"it":[{"ty":"el","bm":0,"hd":false,"mn":"ADBE Vector Shape - Ellipse","nm":"Ellipse Path 1","d":1,"p":{"a":0,"k":[0,0],"ix":3},"s":{"a":0,"k":[236.46,160.849],"ix":2}},{"ty":"st","bm":0,"hd":false,"mn":"ADBE Vector Graphic - Stroke","nm":"Stroke 1","lc":1,"lj":1,"ml":4,"o":{"a":0,"k":100,"ix":4},"w":{"a":0,"k":4,"ix":5},"c":{"a":0,"k":[0.2078,0.2039,0.2039],"ix":3}},{"ty":"fl","bm":0,"hd":false,"mn":"ADBE Vector Graphic - Fill","nm":"Fill 1","c":{"a":1,"k":[{"o":{"x":0.333,"y":0},"i":{"x":0.667,"y":1},"s":[0.7412,0.2039,0.3294],"t":28},{"o":{"x":0.167,"y":0},"i":{"x":0.667,"y":1},"s":[0.1843,0.651,0.3529],"t":33},{"s":[0.1843,0.651,0.3529],"t":44}],"ix":4},"r":1,"o":{"a":0,"k":100,"ix":5}},{"ty":"tr","a":{"a":0,"k":[2.057,0.827],"ix":1},"s":{"a":0,"k":[100,100],"ix":3},"sk":{"a":0,"k":0,"ix":4},"p":{"a":0,"k":[-548.311,-130.49],"ix":2},"r":{"a":0,"k":0,"ix":6},"sa":{"a":0,"k":0,"ix":5},"o":{"a":0,"k":100,"ix":7}}]},{"ty":"gr","bm":0,"hd":false,"mn":"ADBE Vector Group","nm":"Ellipse 3","ix":3,"cix":2,"np":3,"it":[{"ty":"el","bm":0,"hd":false,"mn":"ADBE Vector Shape - Ellipse","nm":"Ellipse Path 1","d":1,"p":{"a":0,"k":[0,0],"ix":3},"s":{"a":0,"k":[236.46,160.849],"ix":2}},{"ty":"st","bm":0,"hd":false,"mn":"ADBE Vector Graphic - Stroke","nm":"Stroke 1","lc":1,"lj":1,"ml":4,"o":{"a":0,"k":100,"ix":4},"w":{"a":0,"k":4,"ix":5},"c":{"a":0,"k":[0.2078,0.2039,0.2039],"ix":3}},{"ty":"fl","bm":0,"hd":false,"mn":"ADBE Vector Graphic - Fill","nm":"Fill 1","c":{"a":0,"k":[0.8314,0.8314,0.8314],"ix":4},"r":1,"o":{"a":0,"k":100,"ix":5}},{"ty":"tr","a":{"a":0,"k":[2.057,0.827],"ix":1},"s":{"a":0,"k":[118.068,118.068],"ix":3},"sk":{"a":0,"k":0,"ix":4},"p":{"a":0,"k":[-547.664,-108.528],"ix":2},"r":{"a":0,"k":0,"ix":6},"sa":{"a":0,"k":0,"ix":5},"o":{"a":0,"k":100,"ix":7}}]},{"ty":"gr","bm":0,"hd":false,"mn":"ADBE Vector Group","nm":"Ellipse 4","ix":4,"cix":2,"np":3,"it":[{"ty":"el","bm":0,"hd":false,"mn":"ADBE Vector Shape - Ellipse","nm":"Ellipse Path 1","d":1,"p":{"a":0,"k":[0,0],"ix":3},"s":{"a":0,"k":[236.46,160.849],"ix":2}},{"ty":"st","bm":0,"hd":false,"mn":"ADBE Vector Graphic - Stroke","nm":"Stroke 1","lc":1,"lj":1,"ml":4,"o":{"a":0,"k":100,"ix":4},"w":{"a":0,"k":4,"ix":5},"c":{"a":0,"k":[0.2078,0.2039,0.2039],"ix":3}},{"ty":"fl","bm":0,"hd":false,"mn":"ADBE Vector Graphic - Fill","nm":"Fill 1","c":{"a":0,"k":[0.6431,0.6314,0.6314],"ix":4},"r":1,"o":{"a":0,"k":100,"ix":5}},{"ty":"tr","a":{"a":0,"k":[2.057,0.827],"ix":1},"s":{"a":0,"k":[118.068,118.068],"ix":3},"sk":{"a":0,"k":0,"ix":4},"p":{"a":0,"k":[-547.664,-84.707],"ix":2},"r":{"a":0,"k":0,"ix":6},"sa":{"a":0,"k":0,"ix":5},"o":{"a":0,"k":100,"ix":7}}]}],"ind":3}],"v":"5.9.4","fr":24,"op":99,"ip":0,"assets":[{"nm":"play","id":"comp_0","fr":60,"layers":[{"ty":4,"nm":"stop","sr":1,"st":0,"op":192.4,"ip":0,"hd":false,"ddd":0,"bm":0,"hasMask":false,"ao":0,"ks":{"a":{"a":0,"k":[215.145,215.144,0],"ix":1},"s":{"a":0,"k":[100,100,100],"ix":6},"sk":{"a":0,"k":0},"p":{"a":0,"k":[359,305,0],"ix":2},"r":{"a":0,"k":0,"ix":10},"sa":{"a":0,"k":0},"o":{"a":0,"k":100,"ix":11}},"ef":[],"shapes":[{"ty":"gr","bm":0,"hd":false,"mn":"ADBE Vector Group","nm":"Grupo 1","ix":1,"cix":2,"np":3,"it":[{"ty":"sh","bm":0,"hd":false,"mn":"ADBE Vector Shape - Group","nm":"Trazado 1","ix":1,"d":1,"ks":{"a":1,"k":[{"o":{"x":1,"y":0},"i":{"x":0,"y":1},"s":[{"c":true,"i":[[31.899,0],[0,0],[0,31.899],[0,0],[-31.899,0],[0,0],[0,-31.899],[0,0]],"o":[[0,0],[-31.899,0],[0,0],[0,-31.899],[0,0],[31.899,0],[0,0],[0,31.899]],"v":[[154.886,212.644],[-154.885,212.644],[-212.644,154.886],[-212.644,-154.885],[-154.885,-212.644],[154.886,-212.644],[212.644,-154.885],[212.644,154.886]]}],"t":28},{"s":[{"c":true,"i":[[0,22.97],[0,0],[0,0],[-8.595,5.33],[-10.274,-5.099],[0,0],[22.837,-11.4],[0,0]],"o":[[0,0],[0,0],[0,-11.469],[8.595,-5.33],[0,0],[22.863,11.348],[0,0],[-20.552,10.259]],"v":[[-212.644,187.413],[-212.644,6.328],[-212.644,-174.757],[-198.023,-201.028],[-167.99,-202.446],[195.825,-21.877],[195.888,33.47],[-167.927,215.07]]}],"t":34}],"ix":2}},{"ty":"fl","bm":0,"hd":false,"mn":"ADBE Vector Graphic - Fill","nm":"Relleno 1","c":{"a":0,"k":[1,0.9804,0.8902],"ix":4},"r":1,"o":{"a":0,"k":100,"ix":5}},{"ty":"tr","a":{"a":0,"k":[0,0],"ix":1},"s":{"a":0,"k":[100,100],"ix":3},"sk":{"a":0,"k":0,"ix":4},"p":{"a":0,"k":[215.144,215.144],"ix":2},"r":{"a":0,"k":0,"ix":6},"sa":{"a":0,"k":0,"ix":5},"o":{"a":0,"k":100,"ix":7}}]}],"ind":1}]}]}